LICENSE
MANIFEST.in
README.rst
setup.cfg
setup.py
versioneer.py
pandahouse/__init__.py
pandahouse/_version.py
pandahouse/convert.py
pandahouse/core.py
pandahouse/http.py
pandahouse/utils.py
pandahouse_v2.egg-info/PKG-INFO
pandahouse_v2.egg-info/SOURCES.txt
pandahouse_v2.egg-info/dependency_links.txt
pandahouse_v2.egg-info/not-zip-safe
pandahouse_v2.egg-info/requires.txt
pandahouse_v2.egg-info/top_level.txt