Metadata-Version: 2.1
Name: pandahouse-v2
Version: 0.1
Summary: Pandas interface for Clickhouse HTTP API forked from pandahouse
Home-page: https://github.com/ayushdeqode/pandahouse
Maintainer: Ayush
Maintainer-email: example@gmail.com
License: BSD
Platform: UNKNOWN
License-File: LICENSE
